grapycal_builtin/__init__.py
grapycal_builtin/container/__init__.py
grapycal_builtin/data/__init__.py
grapycal_builtin/function/__init__.py
grapycal_builtin/function/math.py
grapycal_builtin/interaction/__init__.py
grapycal_builtin/interaction/evalNode.py
grapycal_builtin/interaction/execNode.py
grapycal_builtin/interaction/imagePasteNode.py
grapycal_builtin/interaction/printNode.py
grapycal_builtin/procedural/__init__.py
grapycal_builtin/procedural/forNode.py
grapycal_builtin/procedural/funcDef.py
grapycal_builtin/procedural/limiterNode.py
grapycal_builtin/procedural/procedureNode.py
grapycal_builtin/utils.py
grapycal_builtin-0.11.3.dist-info/METADATA
grapycal_builtin-0.11.3.dist-info/WHEEL
grapycal_builtin-0.11.3.dist-info/RECORD
