Metadata-Version: 2.1
Name: grapycal-builtin
Version: 0.11.3
Summary: Built-in nodes for Grapycal
License: BSD-3-Clause
Author: eri24816
Author-email: a931eric@gmail.com
Requires-Python: >=3.11,<4.0
Classifier: License :: OSI Approved :: BSD License
Classifier: Programming Language :: Python :: 3
Classifier: Programming Language :: Python :: 3.11
Requires-Dist: Pillow (>=10.0.1,<11.0.0)
Requires-Dist: grapycal (>=0.6.1)
Requires-Dist: matplotlib (>=3.8.0,<4.0.0)
Requires-Dist: numpy (>=1.26.0,<2.0.0)
